utility_mcp_server/__init__.py
utility_mcp_server/src/README.md
utility_mcp_server/src/__init__.py
utility_mcp_server/src/api.py
utility_mcp_server/src/main.py
utility_mcp_server/src/mcp.py
utility_mcp_server/src/settings.py
utility_mcp_server/src/stdio_main.py
utility_mcp_server/src/assets/README.md
utility_mcp_server/src/assets/redhat.png
utility_mcp_server/src/oauth/__init__.py
utility_mcp_server/src/oauth/controller.py
utility_mcp_server/src/oauth/handler.py
utility_mcp_server/src/oauth/models.py
utility_mcp_server/src/oauth/routes.py
utility_mcp_server/src/oauth/service.py
utility_mcp_server/src/storage/__init__.py
utility_mcp_server/src/storage/storage_service.py
utility_mcp_server/src/tools/README.md
utility_mcp_server/src/tools/__init__.py
utility_mcp_server/src/tools/release_notes_tool.py
utility_mcp_server/utils/__init__.py
utility_mcp_server/utils/pylogger.py
utility_mcp_server-0.1.1.dist-info/METADATA
utility_mcp_server-0.1.1.dist-info/WHEEL
utility_mcp_server-0.1.1.dist-info/entry_points.txt
utility_mcp_server-0.1.1.dist-info/licenses/LICENSE
utility_mcp_server-0.1.1.dist-info/RECORD
