Metadata-Version: 2.4
Name: utility-mcp-server
Version: 0.1.1
Summary: A utility Model Context Protocol (MCP) server
Project-URL: Homepage, https://github.com/redhat-data-and-ai/utility-mcp-server
Project-URL: Repository, https://github.com/redhat-data-and-ai/utility-mcp-server
Project-URL: Issues, https://github.com/redhat-data-and-ai/utility-mcp-server/issues
Author-email: Jitendra Yejare <jyejare@redhat.com>
License: Apache-2.0
License-File: LICENSE
Keywords: ai-tools,fastmcp,mcp,model-context-protocol,release-notes
Classifier: Development Status :: 4 - Beta
Classifier: Intended Audience :: Developers
Classifier: License :: OSI Approved :: Apache Software License
Classifier: Operating System :: OS Independent
Classifier: Programming Language :: Python :: 3
Classifier: Programming Language :: Python :: 3.12
Classifier: Programming Language :: Python :: 3.13
Classifier: Topic :: Software Development :: Libraries :: Python Modules
Requires-Python: <3.14,>=3.12
Requires-Dist: asyncpg==0.30.0
Requires-Dist: fastapi==0.116.0
Requires-Dist: fastmcp==2.10.4
Requires-Dist: httpx==0.28.1
Requires-Dist: itsdangerous==2.2.0
Requires-Dist: psycopg==3.2.3
Requires-Dist: pydantic-settings==2.10.1
Requires-Dist: pydantic==2.11.7
Requires-Dist: python-dotenv==1.1.1
Requires-Dist: requests-oauthlib==2.0.0
Requires-Dist: structlog==25.4.0
Requires-Dist: uvicorn==0.35.0
Provides-Extra: dev
Requires-Dist: bandit==1.8.6; extra == 'dev'
Requires-Dist: httpx==0.28.1; extra == 'dev'
Requires-Dist: langchain-google-genai==2.1.8; extra == 'dev'
Requires-Dist: langchain-mcp-adapters==0.1.8; extra == 'dev'
Requires-Dist: langgraph==0.5.4; extra == 'dev'
Requires-Dist: mypy==1.16.1; extra == 'dev'
Requires-Dist: pre-commit==4.2.0; extra == 'dev'
Requires-Dist: pytest-asyncio==1.0.0; extra == 'dev'
Requires-Dist: pytest-cov==6.2.1; extra == 'dev'
Requires-Dist: pytest==8.4.1; extra == 'dev'
Requires-Dist: ruff==0.12.2; extra == 'dev'
